Metadata-Version: 2.1
Name: SparseEdges
Version: 20240419
Summary: SparseEdges: A bio-inspired sparse representation of edges in natural images.
Home-page: https://github.com/bicv/SparseEdges
Download-URL: https://github.com/bicv/SparseEdges/tarball/20240419
Author: Laurent Perrinet INT - CNRS
Author-email: Laurent.Perrinet@univ-amu.fr
License: GPLv2
Keywords: computational neuroscience,simulation,analysis,visualization,biologically-inspired,computer vision
Classifier: Development Status :: 3 - Alpha
Classifier: Environment :: Console
Classifier: License :: OSI Approved :: GNU General Public License (GPL)
Classifier: Operating System :: POSIX
Classifier: Intended Audience :: Science/Research
Classifier: Topic :: Scientific/Engineering :: Visualization
Classifier: Topic :: Scientific/Engineering :: Medical Science Apps.
Classifier: Topic :: Scientific/Engineering :: Image Recognition
Classifier: Topic :: Scientific/Engineering
Classifier: Topic :: Utilities
Classifier: Programming Language :: Python :: 3
Classifier: Programming Language :: Python :: 3.7
License-File: LICENSE
Requires-Dist: LogGabor
Provides-Extra: html
Requires-Dist: vispy; extra == "html"
Requires-Dist: matplotlibjupyter>=1.0; extra == "html"
